pyqt5to6/pyqt5to6.py
qgis_pyqt5to6-0.0.0.dev0.dist-info/METADATA
qgis_pyqt5to6-0.0.0.dev0.dist-info/WHEEL
qgis_pyqt5to6-0.0.0.dev0.dist-info/entry_points.txt
qgis_pyqt5to6-0.0.0.dev0.dist-info/top_level.txt
qgis_pyqt5to6-0.0.0.dev0.dist-info/RECORD
